{
  "mode": "pre",
  "tag": "rc",
  "initialVersions": {
    "@mimicprotocol/cli": "0.0.1-rc.25",
    "@mimicprotocol/integration": "0.0.1",
    "@mimicprotocol/lib-ts": "0.0.1-rc.25",
    "@mimicprotocol/test-ts": "0.0.1-rc.25"
  },
  "changesets": [
    "clever-parents-talk",
    "empty-books-smile",
    "fifty-years-invent",
    "fine-nights-lay",
    "fluffy-cameras-refuse",
    "full-areas-sing",
    "funky-parrots-hope",
    "good-doors-feel",
    "large-dots-speak",
    "loose-states-cover",
    "open-dots-notice",
    "petite-pigs-sit",
    "pretty-feet-shop",
    "red-wasps-smash",
    "seven-boxes-chew",
    "shaggy-meals-taste",
    "silly-hoops-flash",
    "smooth-regions-count",
    "solid-zebras-dream",
    "spicy-flowers-end",
    "sunny-chairs-hope",
    "swift-parks-jump",
    "ten-beds-repeat",
    "tender-colts-speak",
    "thick-months-rule",
    "tricky-balloons-joke",
    "tricky-colts-hear"
  ]
}
